flores/__init__.py
flores/__main__.py
flores/exceptions.py
flores/generator.py
flores/logger.py
flores/py.typed
flores/server.py
flores-0.2.0.dist-info/LICENSE
flores-0.2.0.dist-info/METADATA
flores-0.2.0.dist-info/WHEEL
flores-0.2.0.dist-info/entry_points.txt
flores-0.2.0.dist-info/top_level.txt
flores-0.2.0.dist-info/RECORD
