Metadata-Version: 2.1
Name: flores
Version: 0.2.0
Summary: Yet another static site generator.
Author-email: Dimitri Kokkonis <kokkonisd@gmail.com>
License: GPL-3.0
Keywords: static-site-generator,minimal
Classifier: License :: OSI Approved :: GNU General Public License v3 (GPLv3)
Classifier: Development Status :: 4 - Beta
Classifier: Operating System :: POSIX :: Linux
Classifier: Operating System :: Unix
Classifier: Operating System :: MacOS
Classifier: Operating System :: Microsoft :: Windows
Classifier: Topic :: Internet :: WWW/HTTP :: Site Management
Classifier: Intended Audience :: Developers
Classifier: Intended Audience :: Other Audience
Requires-Python: >=3.9
License-File: LICENSE
Requires-Dist: Jinja2
Requires-Dist: libsass
Requires-Dist: pyyaml
Requires-Dist: Markdown
Requires-Dist: pymdown-extensions
Requires-Dist: Pillow
Requires-Dist: Pygments
Provides-Extra: test
Requires-Dist: nox ; extra == 'test'
Requires-Dist: pre-commit ; extra == 'test'
Requires-Dist: pytest ; extra == 'test'
Requires-Dist: pytest-cov ; extra == 'test'
Requires-Dist: requests ; extra == 'test'
